__init__.py
neuroxlink.py
neuroxlink-0.1.3.dist-info/LICENSE
neuroxlink-0.1.3.dist-info/METADATA
neuroxlink-0.1.3.dist-info/WHEEL
neuroxlink-0.1.3.dist-info/top_level.txt
neuroxlink-0.1.3.dist-info/RECORD
