Metadata-Version: 2.1
Name: neuroxlink
Version: 0.1.3
Summary: An experimental mdast parser to browse MyST articles like cough publishers cough cannot even imagine.
Author-email: agahkarakuzu <agahkarakuzu@gmail.com>
License: MIT License
Project-URL: Homepage, https://github.com/neurolibre/neuroxlink
Keywords: myst,mdast,markdown,neurolibre
Classifier: Programming Language :: Python :: 3
Classifier: License :: OSI Approved :: MIT License
Classifier: Operating System :: OS Independent
Requires-Python: >=3.7
License-File: LICENSE
Requires-Dist: requests
Requires-Dist: plotly
Requires-Dist: pandas
Requires-Dist: numpy
